README.md
setup.cfg
setup.py
plodo/__init__.py
plodo/building.py
plodo/deployment.py
plodo/digitalocean.py
plodo/droplets.py
plodo/provisioning.py
plodo.egg-info/PKG-INFO
plodo.egg-info/SOURCES.txt
plodo.egg-info/dependency_links.txt
plodo.egg-info/entry_points.txt
plodo.egg-info/not-zip-safe
plodo.egg-info/requires.txt
plodo.egg-info/top_level.txt
plodo/cli/__init__.py
plodo/cli/build.py
plodo/cli/deploy.py
plodo/cli/provision.py
plodo/cli/scale.py
plodo/cli/shell.py
plodo/cli/utils.py